{
    "Layout": "layout", 
    "Area": "area", 
    "RadialAxis": "radialaxis", 
    "Heatmap": "heatmap", 
    "Contours": "contours", 
    "XBins": "xbins", 
    "Histogram": "histogram", 
    "Annotations": "annotations", 
    "YBins": "ybins", 
    "YAxis": "yaxis", 
    "ErrorX": "error_x", 
    "ErrorY": "error_y", 
    "Histogram2d": "histogram2d", 
    "ColorBar": "colorbar", 
    "Line": "line", 
    "Data": "data", 
    "Legend": "legend", 
    "Box": "box", 
    "Bar": "bar", 
    "AngularAxis": "angularaxis", 
    "Margin": "margin", 
    "Scatter": "scatter", 
    "Figure": "figure", 
    "Stream": "stream", 
    "Annotation": "annotation", 
    "XAxis": "xaxis", 
    "Marker": "marker", 
    "Font": "font", 
    "Histogram2dContour": "histogram2dcontour", 
    "Contour": "contour"
}